_polars_runtime_encrypt/__init__.py
_polars_runtime_encrypt/_polars_runtime.abi3.so
_polars_runtime_encrypt/build_feature_flags.py
polars/__init__.py
polars/__pycache__/__init__.cpython-313.pyc
polars/__pycache__/_cpu_check.cpython-313.pyc
polars/__pycache__/_dependencies.cpython-313.pyc
polars/__pycache__/_plr.cpython-313.pyc
polars/__pycache__/_reexport.cpython-313.pyc
polars/__pycache__/_typing.cpython-313.pyc
polars/__pycache__/api.cpython-313.pyc
polars/__pycache__/config.cpython-313.pyc
polars/__pycache__/exceptions.cpython-313.pyc
polars/__pycache__/plugins.cpython-313.pyc
polars/__pycache__/schema.cpython-313.pyc
polars/__pycache__/selectors.cpython-313.pyc
polars/__pycache__/string_cache.cpython-313.pyc
polars/_cpu_check.py
polars/_dependencies.py
polars/_plr.py
polars/_plr.pyi
polars/_reexport.py
polars/_typing.py
polars/_utils/__init__.py
polars/_utils/__pycache__/__init__.cpython-313.pyc
polars/_utils/__pycache__/async_.cpython-313.pyc
polars/_utils/__pycache__/cache.cpython-313.pyc
polars/_utils/__pycache__/constants.cpython-313.pyc
polars/_utils/__pycache__/convert.cpython-313.pyc
polars/_utils/__pycache__/deprecation.cpython-313.pyc
polars/_utils/__pycache__/getitem.cpython-313.pyc
polars/_utils/__pycache__/logging.cpython-313.pyc
polars/_utils/__pycache__/parquet.cpython-313.pyc
polars/_utils/__pycache__/polars_version.cpython-313.pyc
polars/_utils/__pycache__/pycapsule.cpython-313.pyc
polars/_utils/__pycache__/scan.cpython-313.pyc
polars/_utils/__pycache__/serde.cpython-313.pyc
polars/_utils/__pycache__/slice.cpython-313.pyc
polars/_utils/__pycache__/unstable.cpython-313.pyc
polars/_utils/__pycache__/various.cpython-313.pyc
polars/_utils/__pycache__/wrap.cpython-313.pyc
polars/_utils/async_.py
polars/_utils/cache.py
polars/_utils/cloud.py
polars/_utils/constants.py
polars/_utils/construction/__init__.py
polars/_utils/construction/__pycache__/__init__.cpython-313.pyc
polars/_utils/construction/__pycache__/dataframe.cpython-313.pyc
polars_parquet_encrypt-0.2.0.dist-info/METADATA
polars_parquet_encrypt-0.2.0.dist-info/WHEEL
polars_parquet_encrypt-0.2.0.dist-info/licenses/LICENSE
polars_parquet_encrypt-0.2.0.dist-info/RECORD
