Metadata-Version: 2.4
Name: polars-parquet-encrypt
Version: 0.2.0
Classifier: Development Status :: 4 - Beta
Classifier: Intended Audience :: Developers
Classifier: Intended Audience :: Science/Research
Classifier: License :: OSI Approved :: MIT License
Classifier: Programming Language :: Rust
Classifier: Programming Language :: Python :: 3
Classifier: Programming Language :: Python :: 3.10
Classifier: Programming Language :: Python :: 3.11
Classifier: Programming Language :: Python :: 3.12
Classifier: Programming Language :: Python :: Implementation :: CPython
Classifier: Topic :: Scientific/Engineering
Classifier: Topic :: Software Development :: Libraries
License-File: LICENSE
Summary: Blazingly fast DataFrame library with Parquet encryption support (AES-256-GCM), not production ready
Keywords: polars,parquet,encryption,dataframe,aes-gcm,arrow
Home-Page: https://gitlab.com/anonym1/polars
Author-email: Wei Wang <wei.wang@example.com>
License: MIT
Requires-Python: >=3.10
Project-URL: Homepage, https://gitlab.com/anonym1/polars
Project-URL: Issues, https://gitlab.com/anonym1/polars/-/issues
Project-URL: Repository, https://gitlab.com/anonym1/polars
